{
  "9d0ef7df-df70-4313-84b4-7186b107ea22": {
    "Team Members": null,
    "Photos": null,
    "Campus Manager": null,
    "Map": null,
    "Avatar": null,
    "Contact": null,
    "Address": null,
    "Student Capacity": null,
    "Name": "",
    "Content": []
  },
  "6ca88270-4bfd-47ed-bd6d-884530d6ed9e": {
    "Team Members": null,
    "Photos": null,
    "Campus Manager": null,
    "Map": null,
    "Avatar": null,
    "Contact": null,
    "Address": null,
    "Student Capacity": null,
    "Name": "",
    "Content": []
  },
  "3e5dbf28-8c61-45c7-b1d8-d377e6945d75": {
    "Team Members": null,
    "Photos": [
      "https://s3.us-west-2.amazonaws.com/secure.notion-static.com/41859914-0f11-47f4-ad84-708401faacc9/IMG20221012175358.jpg?X-Amz-Algorithm=AWS4-HMAC-SHA256&X-Amz-Content-Sha256=UNSIGNED-PAYLOAD&X-Amz-Credential=AKIAT73L2G45EIPT3X45%2F20230504%2Fus-west-2%2Fs3%2Faws4_request&X-Amz-Date=20230504T091047Z&X-Amz-Expires=3600&X-Amz-Signature=084fdd420b1eb52e73d3949a91dfabba55d66a6b3b755b11452c1f6d3b9fbde9&X-Amz-SignedHeaders=host&x-id=GetObject",
      "https://s3.us-west-2.amazonaws.com/secure.notion-static.com/ad70a84f-4353-4c26-8379-3f1629083efe/IMG20221006191304.jpg?X-Amz-Algorithm=AWS4-HMAC-SHA256&X-Amz-Content-Sha256=UNSIGNED-PAYLOAD&X-Amz-Credential=AKIAT73L2G45EIPT3X45%2F20230504%2Fus-west-2%2Fs3%2Faws4_request&X-Amz-Date=20230504T091047Z&X-Amz-Expires=3600&X-Amz-Signature=dcccf661226260631dcb6c4a4c25b341ef78c5253544fb6822cb92ce37bf2970&X-Amz-SignedHeaders=host&x-id=GetObject",
      "https://s3.us-west-2.amazonaws.com/secure.notion-static.com/04da20c1-8879-4414-8024-76e7e2c60eca/IMG-20221010-WA0028_%281%29.jpg?X-Amz-Algorithm=AWS4-HMAC-SHA256&X-Amz-Content-Sha256=UNSIGNED-PAYLOAD&X-Amz-Credential=AKIAT73L2G45EIPT3X45%2F20230504%2Fus-west-2%2Fs3%2Faws4_request&X-Amz-Date=20230504T091047Z&X-Amz-Expires=3600&X-Amz-Signature=c38334eed1d44240d4ac729ace98fa52c65f56770f23d3d275007aff07026dcf&X-Amz-SignedHeaders=host&x-id=GetObject",
      "https://s3.us-west-2.amazonaws.com/secure.notion-static.com/987a316d-5521-4d8c-8df9-d6dd326424f1/WhatsApp_Image_2022-10-17_at_4.15.13_PM.jpeg?X-Amz-Algorithm=AWS4-HMAC-SHA256&X-Amz-Content-Sha256=UNSIGNED-PAYLOAD&X-Amz-Credential=AKIAT73L2G45EIPT3X45%2F20230504%2Fus-west-2%2Fs3%2Faws4_request&X-Amz-Date=20230504T091047Z&X-Amz-Expires=3600&X-Amz-Signature=d1ef9c5f05b4a6387193b35e50875b40c60a286ee7d460aab2f529f570b5b444&X-Amz-SignedHeaders=host&x-id=GetObject",
      "https://s3.us-west-2.amazonaws.com/secure.notion-static.com/bb11db87-b208-447b-80d1-04381271b501/WhatsApp_Image_2022-10-17_at_4.15.13_PM_%281%29.jpeg?X-Amz-Algorithm=AWS4-HMAC-SHA256&X-Amz-Content-Sha256=UNSIGNED-PAYLOAD&X-Amz-Credential=AKIAT73L2G45EIPT3X45%2F20230504%2Fus-west-2%2Fs3%2Faws4_request&X-Amz-Date=20230504T091047Z&X-Amz-Expires=3600&X-Amz-Signature=3dd14b7897c8cc658d4164bdb5a86efb54d2cbc8a5c23945c51a079dd6e6db8e&X-Amz-SignedHeaders=host&x-id=GetObject",
      "https://s3.us-west-2.amazonaws.com/secure.notion-static.com/ac836838-c2f9-4685-9328-bc05bac6407c/WhatsApp_Image_2022-10-17_at_4.15.14_PM.jpeg?X-Amz-Algorithm=AWS4-HMAC-SHA256&X-Amz-Content-Sha256=UNSIGNED-PAYLOAD&X-Amz-Credential=AKIAT73L2G45EIPT3X45%2F20230504%2Fus-west-2%2Fs3%2Faws4_request&X-Amz-Date=20230504T091047Z&X-Amz-Expires=3600&X-Amz-Signature=29a736149a95dc1cf884b90b5887cb534057c8d219a114f70145b4067c3c852d&X-Amz-SignedHeaders=host&x-id=GetObject"
    ],
    "Campus Manager": "Aarzoo Jolly ",
    "Map": null,
    "Avatar": null,
    "Contact": null,
    "Address": "Navgurukul Amravati Campus.\nPrabodhini College, Near \nTapovan gate.\nShivneri Colony, Amravati, Maharashtra 444602",
    "Student Capacity": null,
    "Name": "Amravati Campus",
    "Content": []
  },
  "c90f370b-bf40-4c4e-9878-1ba401eca92a": {
    "Team Members": null,
    "Photos": [
      "https://s3.us-west-2.amazonaws.com/secure.notion-static.com/c3d2bde0-ab6d-46ec-ac42-5f13b719b612/WhatsApp_Image_2022-11-05_at_11.55.55_AM.jpeg?X-Amz-Algorithm=AWS4-HMAC-SHA256&X-Amz-Content-Sha256=UNSIGNED-PAYLOAD&X-Amz-Credential=AKIAT73L2G45EIPT3X45%2F20230504%2Fus-west-2%2Fs3%2Faws4_request&X-Amz-Date=20230504T091047Z&X-Amz-Expires=3600&X-Amz-Signature=ec9d14789454be551ea63af32b8d26e3de26d17467edf2277765bca230333aaf&X-Amz-SignedHeaders=host&x-id=GetObject",
      "https://s3.us-west-2.amazonaws.com/secure.notion-static.com/4e9de257-e64f-43bd-8aad-1d4f395878cc/WhatsApp_Image_2022-11-05_at_11.55.55_AM_%281%29.jpeg?X-Amz-Algorithm=AWS4-HMAC-SHA256&X-Amz-Content-Sha256=UNSIGNED-PAYLOAD&X-Amz-Credential=AKIAT73L2G45EIPT3X45%2F20230504%2Fus-west-2%2Fs3%2Faws4_request&X-Amz-Date=20230504T091047Z&X-Amz-Expires=3600&X-Amz-Signature=cf8383fd5eb91b85aba580e2a62edbba37194911a9ec17969cf85e43a9506663&X-Amz-SignedHeaders=host&x-id=GetObject",
      "https://s3.us-west-2.amazonaws.com/secure.notion-static.com/d3ca91b8-6a7e-46f5-8381-459d9365cb00/WhatsApp_Image_2022-11-05_at_11.56.09_AM.jpeg?X-Amz-Algorithm=AWS4-HMAC-SHA256&X-Amz-Content-Sha256=UNSIGNED-PAYLOAD&X-Amz-Credential=AKIAT73L2G45EIPT3X45%2F20230504%2Fus-west-2%2Fs3%2Faws4_request&X-Amz-Date=20230504T091047Z&X-Amz-Expires=3600&X-Amz-Signature=70bd635a509311c1168ca71bfaa819d176bcf50574df82518c2af6c367bc6672&X-Amz-SignedHeaders=host&x-id=GetObject",
      "https://s3.us-west-2.amazonaws.com/secure.notion-static.com/7b3cac10-8ed7-4742-b78d-6fb89201a96d/WhatsApp_Image_2022-11-05_at_11.58.42_AM.jpeg?X-Amz-Algorithm=AWS4-HMAC-SHA256&X-Amz-Content-Sha256=UNSIGNED-PAYLOAD&X-Amz-Credential=AKIAT73L2G45EIPT3X45%2F20230504%2Fus-west-2%2Fs3%2Faws4_request&X-Amz-Date=20230504T091047Z&X-Amz-Expires=3600&X-Amz-Signature=5c12065da20f8efef777fa681d0e7fcbe2dbb8fd1e17f915d9b18e60674ff4c0&X-Amz-SignedHeaders=host&x-id=GetObject",
      "https://s3.us-west-2.amazonaws.com/secure.notion-static.com/bb7e2f7b-a436-4102-9817-8cfe75c1523c/WhatsApp_Image_2022-11-05_at_11.58.42_AM_%281%29.jpeg?X-Amz-Algorithm=AWS4-HMAC-SHA256&X-Amz-Content-Sha256=UNSIGNED-PAYLOAD&X-Amz-Credential=AKIAT73L2G45EIPT3X45%2F20230504%2Fus-west-2%2Fs3%2Faws4_request&X-Amz-Date=20230504T091047Z&X-Amz-Expires=3600&X-Amz-Signature=2293cbe6c27acda49d4afbb799a29fcb0a7c002608a9af683f449262e9463fbc&X-Amz-SignedHeaders=host&x-id=GetObject"
    ],
    "Campus Manager": "Ishita and Kankana",
    "Map": null,
    "Avatar": null,
    "Contact": "ishita@navgurukul.org  kankana@navgurukul.org",
    "Address": "Navgurukul DSEU Campus\nDwarka Sector 9, Dwarka, Delhi, 110075",
    "Student Capacity": "100",
    "Name": "Delhi Campus",
    "Content": []
  },
  "74efa683-89a2-4251-9b80-caaff0861f91": {
    "Team Members": null,
    "Photos": [
      "https://s3.us-west-2.amazonaws.com/secure.notion-static.com/4630b4e2-0f05-4259-8637-82f798fa2056/WhatsApp_Image_2022-03-31_at_5.29.28_PM.jpeg?X-Amz-Algorithm=AWS4-HMAC-SHA256&X-Amz-Content-Sha256=UNSIGNED-PAYLOAD&X-Amz-Credential=AKIAT73L2G45EIPT3X45%2F20230504%2Fus-west-2%2Fs3%2Faws4_request&X-Amz-Date=20230504T091047Z&X-Amz-Expires=3600&X-Amz-Signature=6ae72dd917e0e26fa1f8fc2334bfe422a0f1be570439002ad40aebcbdccb456c&X-Amz-SignedHeaders=host&x-id=GetObject",
      "https://s3.us-west-2.amazonaws.com/secure.notion-static.com/5be6a47c-a644-436e-a8d7-79b93566a413/WhatsApp_Image_2022-03-31_at_5.29.30_PM.jpeg?X-Amz-Algorithm=AWS4-HMAC-SHA256&X-Amz-Content-Sha256=UNSIGNED-PAYLOAD&X-Amz-Credential=AKIAT73L2G45EIPT3X45%2F20230504%2Fus-west-2%2Fs3%2Faws4_request&X-Amz-Date=20230504T091047Z&X-Amz-Expires=3600&X-Amz-Signature=bd0e163d624806e2ecab8e2bb5f46943f5136014db4a41d36c7d303b7d76ce8e&X-Amz-SignedHeaders=host&x-id=GetObject",
      "https://s3.us-west-2.amazonaws.com/secure.notion-static.com/db8e090f-fdad-4c4e-805a-9a018ccd24ec/IMG_20220207_164416.jpg?X-Amz-Algorithm=AWS4-HMAC-SHA256&X-Amz-Content-Sha256=UNSIGNED-PAYLOAD&X-Amz-Credential=AKIAT73L2G45EIPT3X45%2F20230504%2Fus-west-2%2Fs3%2Faws4_request&X-Amz-Date=20230504T091047Z&X-Amz-Expires=3600&X-Amz-Signature=51fc84daee1016cd32d4cc4149dddd989be0a39d1a0c48fa835289d2eab371e5&X-Amz-SignedHeaders=host&x-id=GetObject",
      "https://s3.us-west-2.amazonaws.com/secure.notion-static.com/1721504f-b110-47eb-ab06-33a31c48da81/IMG_20201114_202217.jpg?X-Amz-Algorithm=AWS4-HMAC-SHA256&X-Amz-Content-Sha256=UNSIGNED-PAYLOAD&X-Amz-Credential=AKIAT73L2G45EIPT3X45%2F20230504%2Fus-west-2%2Fs3%2Faws4_request&X-Amz-Date=20230504T091047Z&X-Amz-Expires=3600&X-Amz-Signature=59edeb8295af7a6792c049952fb97b933d9ec329e7037a0cd1e8fc3ac0fedba3&X-Amz-SignedHeaders=host&x-id=GetObject",
      "https://s3.us-west-2.amazonaws.com/secure.notion-static.com/f52daf34-62fc-4404-9204-477feaa62cfc/IMG20181216153951.jpg?X-Amz-Algorithm=AWS4-HMAC-SHA256&X-Amz-Content-Sha256=UNSIGNED-PAYLOAD&X-Amz-Credential=AKIAT73L2G45EIPT3X45%2F20230504%2Fus-west-2%2Fs3%2Faws4_request&X-Amz-Date=20230504T091047Z&X-Amz-Expires=3600&X-Amz-Signature=94e1fb01e5ed6b2cd05dea2e0573acb4f5ef1e26064dd61ef94109066ef986e3&X-Amz-SignedHeaders=host&x-id=GetObject",
      "https://s3.us-west-2.amazonaws.com/secure.notion-static.com/b1145fe2-a6d2-4bcd-b8bf-3a3190c2cc56/IMG20201114194400.jpg?X-Amz-Algorithm=AWS4-HMAC-SHA256&X-Amz-Content-Sha256=UNSIGNED-PAYLOAD&X-Amz-Credential=AKIAT73L2G45EIPT3X45%2F20230504%2Fus-west-2%2Fs3%2Faws4_request&X-Amz-Date=20230504T091047Z&X-Amz-Expires=3600&X-Amz-Signature=e91f3eba52ac25979649d81e914ad9f80816309cad8b187d27846130a1a5b299&X-Amz-SignedHeaders=host&x-id=GetObject"
    ],
    "Campus Manager": "Santosh Maurya",
    "Map": "https://www.google.com/maps/embed?pb=!1m18!1m12!1m3!1d3376.8260602373425!2d76.342372315167!3d32.18196488115586!2m3!1f0!2f0!3f0!3m2!1i1024!2i768!4f13.1!3m3!1m2!1s0x391b51969f04e4b9%3A0x26c06669e05c031b!2sNavGurukul Dharamsala Campus!5e0!3m2!1sen!2sin!4v1648545626708!5m2!1sen!2sin",
    "Avatar": "https://s3.us-west-2.amazonaws.com/secure.notion-static.com/5c1b4b9e-0cf1-470c-82ea-1727722273c2/avatar-4.png?X-Amz-Algorithm=AWS4-HMAC-SHA256&X-Amz-Content-Sha256=UNSIGNED-PAYLOAD&X-Amz-Credential=AKIAT73L2G45EIPT3X45%2F20230504%2Fus-west-2%2Fs3%2Faws4_request&X-Amz-Date=20230504T091047Z&X-Amz-Expires=3600&X-Amz-Signature=74fe3e960bbd5dafa4a8f9405bced9c2870db3c407ae1e4991c2e02d8b2763cd&X-Amz-SignedHeaders=host&x-id=GetObject",
    "Contact": "santosh22@navgurukul.org",
    "Address": "Navgurukul Dharmshala Campus. Ward number 202, Sukkhad, Dharmshala, Himachal Pradesh. 176057",
    "Student Capacity": "50",
    "Name": "Dharmshala Campus",
    "Content": []
  },
  "9ff85995-5ac0-4e33-aa63-17605a4fc72d": {
    "Team Members": "2",
    "Photos": [
      "https://s3.us-west-2.amazonaws.com/secure.notion-static.com/2d8ff371-0750-426b-9d25-c87f345bee91/WhatsApp_Image_2022-03-25_at_5.55.01_PM.jpeg?X-Amz-Algorithm=AWS4-HMAC-SHA256&X-Amz-Content-Sha256=UNSIGNED-PAYLOAD&X-Amz-Credential=AKIAT73L2G45EIPT3X45%2F20230504%2Fus-west-2%2Fs3%2Faws4_request&X-Amz-Date=20230504T091047Z&X-Amz-Expires=3600&X-Amz-Signature=b0a8325444bde75f42af3c9ddd55e03454ae7c357c7f64717f7628738ba5031b&X-Amz-SignedHeaders=host&x-id=GetObject",
      "https://s3.us-west-2.amazonaws.com/secure.notion-static.com/fe1495ba-4f18-49be-9932-a20131530288/WhatsApp_Image_2022-03-25_at_5.55.01_PM_%281%29.jpeg?X-Amz-Algorithm=AWS4-HMAC-SHA256&X-Amz-Content-Sha256=UNSIGNED-PAYLOAD&X-Amz-Credential=AKIAT73L2G45EIPT3X45%2F20230504%2Fus-west-2%2Fs3%2Faws4_request&X-Amz-Date=20230504T091047Z&X-Amz-Expires=3600&X-Amz-Signature=0f9a4bcdec9aa989bc12937ad1893ca89b13539964d87d237bad218c73d51056&X-Amz-SignedHeaders=host&x-id=GetObject",
      "https://s3.us-west-2.amazonaws.com/secure.notion-static.com/98c61fa9-ced2-44e2-b00b-437c81e269f8/WhatsApp_Image_2022-03-25_at_5.55.01_PM_%283%29.jpeg?X-Amz-Algorithm=AWS4-HMAC-SHA256&X-Amz-Content-Sha256=UNSIGNED-PAYLOAD&X-Amz-Credential=AKIAT73L2G45EIPT3X45%2F20230504%2Fus-west-2%2Fs3%2Faws4_request&X-Amz-Date=20230504T091047Z&X-Amz-Expires=3600&X-Amz-Signature=5cbbbfd2e7eef429281f4a346f3f9b4d3a67496cc80329f582a53aba2b9f253b&X-Amz-SignedHeaders=host&x-id=GetObject",
      "https://s3.us-west-2.amazonaws.com/secure.notion-static.com/86da4be4-ecd7-4698-ba3d-f64cd11c090f/WhatsApp_Image_2022-03-25_at_5.55.01_PM_%282%29.jpeg?X-Amz-Algorithm=AWS4-HMAC-SHA256&X-Amz-Content-Sha256=UNSIGNED-PAYLOAD&X-Amz-Credential=AKIAT73L2G45EIPT3X45%2F20230504%2Fus-west-2%2Fs3%2Faws4_request&X-Amz-Date=20230504T091047Z&X-Amz-Expires=3600&X-Amz-Signature=4c2ee1174a10cd6010f87fa89105472ab853a335438af0d8b3e923a9bc580a02&X-Amz-SignedHeaders=host&x-id=GetObject"
    ],
    "Campus Manager": "Kajal Rawat",
    "Map": "https://www.google.com/maps/embed?pb=!1m18!1m12!1m3!1d3648.7921500150846!2d91.28128251498349!3d23.861513384534632!2m3!1f0!2f0!3f0!3m2!1i1024!2i768!4f13.1!3m3!1m2!1s0x3753f6ae8cdb116b%3A0xf73703350dc257a0!2sShaheed%20Bhagat%20Singh%20Youth%20Hostel!5e0!3m2!1sen!2sin!4v1648272294495!5m2!1sen!2sin",
    "Avatar": "https://s3.us-west-2.amazonaws.com/secure.notion-static.com/4136baef-5071-45e9-a086-860701cd7cff/avatar-3.png?X-Amz-Algorithm=AWS4-HMAC-SHA256&X-Amz-Content-Sha256=UNSIGNED-PAYLOAD&X-Amz-Credential=AKIAT73L2G45EIPT3X45%2F20230504%2Fus-west-2%2Fs3%2Faws4_request&X-Amz-Date=20230504T091047Z&X-Amz-Expires=3600&X-Amz-Signature=ab5b1284fd7180e42d92aac94742f2f9f368d2a407d3745ca91f0dd6067553af&X-Amz-SignedHeaders=host&x-id=GetObject",
    "Contact": "kajalk20@navgurukul.org",
    "Address": "V76M+J95,Kunjaban Township, Shaheed Bhagat Singh Youth Hostal ,VIP Rode, Agartala, Tripura - 799010",
    "Student Capacity": "150",
    "Name": "Tripura Campus",
    "Content": []
  },
  "e8006591-351e-4ef6-a7aa-cd2e4a220b8a": {
    "Team Members": "5",
    "Photos": [
      "https://s3.us-west-2.amazonaws.com/secure.notion-static.com/9cf49124-1c4d-46e0-a89e-e5aaa5b0a336/WhatsApp_Image_2022-03-30_at_3.24.43_PM.jpeg?X-Amz-Algorithm=AWS4-HMAC-SHA256&X-Amz-Content-Sha256=UNSIGNED-PAYLOAD&X-Amz-Credential=AKIAT73L2G45EIPT3X45%2F20230504%2Fus-west-2%2Fs3%2Faws4_request&X-Amz-Date=20230504T091047Z&X-Amz-Expires=3600&X-Amz-Signature=4893da2307e042c481790491d5117636958b27c948cb3cba5ea559235497c741&X-Amz-SignedHeaders=host&x-id=GetObject",
      "https://s3.us-west-2.amazonaws.com/secure.notion-static.com/49d7ebc2-d0e6-4263-a1b4-968f718c6339/WhatsApp_Image_2022-03-30_at_3.24.40_PM.jpeg?X-Amz-Algorithm=AWS4-HMAC-SHA256&X-Amz-Content-Sha256=UNSIGNED-PAYLOAD&X-Amz-Credential=AKIAT73L2G45EIPT3X45%2F20230504%2Fus-west-2%2Fs3%2Faws4_request&X-Amz-Date=20230504T091047Z&X-Amz-Expires=3600&X-Amz-Signature=0b92bd63266687740911d8194238a08d2e68f4e72469eb88672fb5a2f2a46490&X-Amz-SignedHeaders=host&x-id=GetObject",
      "https://s3.us-west-2.amazonaws.com/secure.notion-static.com/e25ff736-3c35-4f8c-ad36-e99fcdbc7d03/1630303066963.jpg?X-Amz-Algorithm=AWS4-HMAC-SHA256&X-Amz-Content-Sha256=UNSIGNED-PAYLOAD&X-Amz-Credential=AKIAT73L2G45EIPT3X45%2F20230504%2Fus-west-2%2Fs3%2Faws4_request&X-Amz-Date=20230504T091047Z&X-Amz-Expires=3600&X-Amz-Signature=c8b2062e9ae086e58b98408cd497969af4935b1f4286da2fa82dae7d226f485e&X-Amz-SignedHeaders=host&x-id=GetObject",
      "https://s3.us-west-2.amazonaws.com/secure.notion-static.com/2c723df8-36e2-4a2d-9773-38b3352068d1/1630303066662.jpg?X-Amz-Algorithm=AWS4-HMAC-SHA256&X-Amz-Content-Sha256=UNSIGNED-PAYLOAD&X-Amz-Credential=AKIAT73L2G45EIPT3X45%2F20230504%2Fus-west-2%2Fs3%2Faws4_request&X-Amz-Date=20230504T091047Z&X-Amz-Expires=3600&X-Amz-Signature=529fe3e40fe3d1131c8cc36bb0d25f75203db08aa45634d4fceb4739ce92730b&X-Amz-SignedHeaders=host&x-id=GetObject",
      "https://s3.us-west-2.amazonaws.com/secure.notion-static.com/639cb4c1-fd66-439a-bccd-80bb53f79d8d/1625977779985.jpg?X-Amz-Algorithm=AWS4-HMAC-SHA256&X-Amz-Content-Sha256=UNSIGNED-PAYLOAD&X-Amz-Credential=AKIAT73L2G45EIPT3X45%2F20230504%2Fus-west-2%2Fs3%2Faws4_request&X-Amz-Date=20230504T091047Z&X-Amz-Expires=3600&X-Amz-Signature=75fca0352fe81030165f7c1bc9057e7e486c493f054e42143aee213160832660&X-Amz-SignedHeaders=host&x-id=GetObject",
      "https://s3.us-west-2.amazonaws.com/secure.notion-static.com/a0e0ab46-5d85-4537-82dc-e4521f8e441b/WhatsApp_Image_2022-03-30_at_3.24.39_PM.jpeg?X-Amz-Algorithm=AWS4-HMAC-SHA256&X-Amz-Content-Sha256=UNSIGNED-PAYLOAD&X-Amz-Credential=AKIAT73L2G45EIPT3X45%2F20230504%2Fus-west-2%2Fs3%2Faws4_request&X-Amz-Date=20230504T091047Z&X-Amz-Expires=3600&X-Amz-Signature=57960a5dea5fded97fea962d93b743b65ece237819e494716df3f581db54ea4d&X-Amz-SignedHeaders=host&x-id=GetObject"
    ],
    "Campus Manager": "Rajalakshmi P",
    "Map": "https://www.google.com/maps/embed?pb=!1m18!1m12!1m3!1d3889.1455662928365!2d77.68612241482124!3d12.898359890903984!2m3!1f0!2f0!3f0!3m2!1i1024!2i768!4f13.1!3m3!1m2!1s0x3bae137aa6184017%3A0xb8ee2b373af46534!2sNavGurukul%20Sarjapur%20Campus!5e0!3m2!1sen!2sin!4v1648272256943!5m2!1sen!2sin",
    "Avatar": "https://s3.us-west-2.amazonaws.com/secure.notion-static.com/d3ae9549-1698-472b-a211-3f93c4fc6421/avatar-2.png?X-Amz-Algorithm=AWS4-HMAC-SHA256&X-Amz-Content-Sha256=UNSIGNED-PAYLOAD&X-Amz-Credential=AKIAT73L2G45EIPT3X45%2F20230504%2Fus-west-2%2Fs3%2Faws4_request&X-Amz-Date=20230504T091047Z&X-Amz-Expires=3600&X-Amz-Signature=1de49f6e5bdf9aad68cd50b3a94e0746b8e1f8f1fed197cf89b6480c08e0ecad&X-Amz-SignedHeaders=host&x-id=GetObject",
    "Contact": "rajalakshmi@Navgurukul.org",
    "Address": "No. 68/16A, Halanayakanahalli village, Varthur, East, Uttarahalli Hobli, Bangalore Karnataka 560035",
    "Student Capacity": "130",
    "Name": "Sarjapur Campus",
    "Content": []
  },
  "686fb76f-f629-4e83-b00e-23cd63b65c53": {
    "Team Members": "4",
    "Photos": [
      "https://s3.us-west-2.amazonaws.com/secure.notion-static.com/bb887a34-1c46-4f6f-9506-e70bc0c4959f/WhatsApp_Image_2021-09-28_at_10.27.25_AM.jpeg?X-Amz-Algorithm=AWS4-HMAC-SHA256&X-Amz-Content-Sha256=UNSIGNED-PAYLOAD&X-Amz-Credential=AKIAT73L2G45EIPT3X45%2F20230504%2Fus-west-2%2Fs3%2Faws4_request&X-Amz-Date=20230504T091047Z&X-Amz-Expires=3600&X-Amz-Signature=b863ebf19d0218f1e00fe35a325fe2a2431bc3810daedafdb3847c2b91e4e7ba&X-Amz-SignedHeaders=host&x-id=GetObject",
      "https://s3.us-west-2.amazonaws.com/secure.notion-static.com/95a9dbde-e8d6-4142-8dd2-9e01fc1375d3/WhatsApp_Image_2021-09-28_at_10.27.27_AM_%281%29.jpeg?X-Amz-Algorithm=AWS4-HMAC-SHA256&X-Amz-Content-Sha256=UNSIGNED-PAYLOAD&X-Amz-Credential=AKIAT73L2G45EIPT3X45%2F20230504%2Fus-west-2%2Fs3%2Faws4_request&X-Amz-Date=20230504T091047Z&X-Amz-Expires=3600&X-Amz-Signature=e13d949d7c43e6646e10343d38d1bae2935d28e58c105615065ded586c3977c4&X-Amz-SignedHeaders=host&x-id=GetObject",
      "https://s3.us-west-2.amazonaws.com/secure.notion-static.com/6cccaaeb-341f-4dfd-9b25-17b98cb09735/WhatsApp_Image_2021-09-28_at_10.29.49_AM.jpeg?X-Amz-Algorithm=AWS4-HMAC-SHA256&X-Amz-Content-Sha256=UNSIGNED-PAYLOAD&X-Amz-Credential=AKIAT73L2G45EIPT3X45%2F20230504%2Fus-west-2%2Fs3%2Faws4_request&X-Amz-Date=20230504T091047Z&X-Amz-Expires=3600&X-Amz-Signature=7614910056fba51670a721a360b40fcda63e2593a072e0686dc7992aa2f592b2&X-Amz-SignedHeaders=host&x-id=GetObject",
      "https://s3.us-west-2.amazonaws.com/secure.notion-static.com/0893706a-abfa-4526-b9d9-006d6d76a847/WhatsApp_Image_2021-09-28_at_10.30.19_AM.jpeg?X-Amz-Algorithm=AWS4-HMAC-SHA256&X-Amz-Content-Sha256=UNSIGNED-PAYLOAD&X-Amz-Credential=AKIAT73L2G45EIPT3X45%2F20230504%2Fus-west-2%2Fs3%2Faws4_request&X-Amz-Date=20230504T091047Z&X-Amz-Expires=3600&X-Amz-Signature=c3b6dcfbe848615d50935601bf22606eec4acc88e48946e7e589b8bbd948886a&X-Amz-SignedHeaders=host&x-id=GetObject"
    ],
    "Campus Manager": "Rupali Singh",
    "Map": "https://www.google.com/maps/embed?pb=!1m18!1m12!1m3!1d3889.6148868269765!2d77.7108817148209!3d12.86813239092383!2m3!1f0!2f0!3f0!3m2!1i1024!2i768!4f13.1!3m3!1m2!1s0x3bae6d4d12f750d7%3A0x74f3ba658fbf7d95!2sNavGurukul%20Bangalore%20Campus!5e0!3m2!1sen!2sin!4v1648272183706!5m2!1sen!2sin",
    "Avatar": "https://s3.us-west-2.amazonaws.com/secure.notion-static.com/db5b8c43-7142-4492-af1a-5b27ec4c3cf3/avatar-1.png?X-Amz-Algorithm=AWS4-HMAC-SHA256&X-Amz-Content-Sha256=UNSIGNED-PAYLOAD&X-Amz-Credential=AKIAT73L2G45EIPT3X45%2F20230504%2Fus-west-2%2Fs3%2Faws4_request&X-Amz-Date=20230504T091047Z&X-Amz-Expires=3600&X-Amz-Signature=b9c6af13f228584ffe432f054c3b0854710de90f03abe0eeeb1d99608c764419&X-Amz-SignedHeaders=host&x-id=GetObject",
    "Contact": "rupalisingh20@navgurukul.org",
    "Address": "45/1, 45/2\nAvalahalli Huskur Panchayat\nSarjapura Hobli\nAnekal Taluk District\nBengaluru\nKarnataka\n560099",
    "Student Capacity": "120",
    "Name": "Bangalore Campus",
    "Content": []
  },
  "1ccbbdb3-b485-49e2-becc-78d329b5955c": {
    "Team Members": "11",
    "Photos": [
      "https://s3.us-west-2.amazonaws.com/secure.notion-static.com/40f886ad-c8ca-4427-890c-4442b8e63e89/WhatsApp_Image_2022-04-05_at_3.17.38_PM.jpeg?X-Amz-Algorithm=AWS4-HMAC-SHA256&X-Amz-Content-Sha256=UNSIGNED-PAYLOAD&X-Amz-Credential=AKIAT73L2G45EIPT3X45%2F20230504%2Fus-west-2%2Fs3%2Faws4_request&X-Amz-Date=20230504T091047Z&X-Amz-Expires=3600&X-Amz-Signature=ebeafa4eac27f0f7a29a7be0f5de6c07980c8e7d6ffae83fd40de00a5f305317&X-Amz-SignedHeaders=host&x-id=GetObject",
      "https://s3.us-west-2.amazonaws.com/secure.notion-static.com/172327c0-d700-441c-afa7-8644858f6abc/WhatsApp_Image_2022-04-05_at_3.13.13_PM%282%29.jpeg?X-Amz-Algorithm=AWS4-HMAC-SHA256&X-Amz-Content-Sha256=UNSIGNED-PAYLOAD&X-Amz-Credential=AKIAT73L2G45EIPT3X45%2F20230504%2Fus-west-2%2Fs3%2Faws4_request&X-Amz-Date=20230504T091047Z&X-Amz-Expires=3600&X-Amz-Signature=3b59dcce39e4fe76f61c354e551f2f932d0078c363b5ce5715c9dd9e302c2f15&X-Amz-SignedHeaders=host&x-id=GetObject",
      "https://s3.us-west-2.amazonaws.com/secure.notion-static.com/2666c3eb-21a3-417c-9f3a-67c87cef8282/WhatsApp_Image_2022-04-05_at_3.17.37_PM.jpeg?X-Amz-Algorithm=AWS4-HMAC-SHA256&X-Amz-Content-Sha256=UNSIGNED-PAYLOAD&X-Amz-Credential=AKIAT73L2G45EIPT3X45%2F20230504%2Fus-west-2%2Fs3%2Faws4_request&X-Amz-Date=20230504T091047Z&X-Amz-Expires=3600&X-Amz-Signature=974e178dc9935fcbf93fde960977dfdad7e46d9411f3d9c3052e21cdc943fa62&X-Amz-SignedHeaders=host&x-id=GetObject",
      "https://s3.us-west-2.amazonaws.com/secure.notion-static.com/291b4da4-5196-4084-bcb2-8c15058cd310/WhatsApp_Image_2022-01-10_at_8.45.27_PM.jpeg?X-Amz-Algorithm=AWS4-HMAC-SHA256&X-Amz-Content-Sha256=UNSIGNED-PAYLOAD&X-Amz-Credential=AKIAT73L2G45EIPT3X45%2F20230504%2Fus-west-2%2Fs3%2Faws4_request&X-Amz-Date=20230504T091047Z&X-Amz-Expires=3600&X-Amz-Signature=0914bd865b58c588c0271bcc6551f2b3d51ced51ae2f514e87325c4ab60f94c6&X-Amz-SignedHeaders=host&x-id=GetObject",
      "https://s3.us-west-2.amazonaws.com/secure.notion-static.com/91aa9b1d-493e-4192-934a-48e575e103a8/WhatsApp_Image_2022-04-05_at_3.17.36_PM.jpeg?X-Amz-Algorithm=AWS4-HMAC-SHA256&X-Amz-Content-Sha256=UNSIGNED-PAYLOAD&X-Amz-Credential=AKIAT73L2G45EIPT3X45%2F20230504%2Fus-west-2%2Fs3%2Faws4_request&X-Amz-Date=20230504T091047Z&X-Amz-Expires=3600&X-Amz-Signature=16b8959539c93bcec9395659291c050746b4ff572020cc73cb2b34fdabae46c2&X-Amz-SignedHeaders=host&x-id=GetObject",
      "https://s3.us-west-2.amazonaws.com/secure.notion-static.com/9721c133-3035-4943-8d00-b0c9348014b8/WhatsApp_Image_2022-04-05_at_3.10.59_PM.jpeg?X-Amz-Algorithm=AWS4-HMAC-SHA256&X-Amz-Content-Sha256=UNSIGNED-PAYLOAD&X-Amz-Credential=AKIAT73L2G45EIPT3X45%2F20230504%2Fus-west-2%2Fs3%2Faws4_request&X-Amz-Date=20230504T091047Z&X-Amz-Expires=3600&X-Amz-Signature=7ebb7b6e0ceb658f01d7b9637b871360948835f29cafeeaf8fcdeeb18455f8da&X-Amz-SignedHeaders=host&x-id=GetObject",
      "https://s3.us-west-2.amazonaws.com/secure.notion-static.com/85fc80c5-7382-4565-833d-9a92cbfde45c/WhatsApp_Image_2022-04-05_at_3.13.13_PM%281%29.jpeg?X-Amz-Algorithm=AWS4-HMAC-SHA256&X-Amz-Content-Sha256=UNSIGNED-PAYLOAD&X-Amz-Credential=AKIAT73L2G45EIPT3X45%2F20230504%2Fus-west-2%2Fs3%2Faws4_request&X-Amz-Date=20230504T091047Z&X-Amz-Expires=3600&X-Amz-Signature=20563739baa18a86b14a82dfa015be9ff8aa3bf752dad4173d2bc648ae8a9e2a&X-Amz-SignedHeaders=host&x-id=GetObject",
      "https://s3.us-west-2.amazonaws.com/secure.notion-static.com/b43b9be0-a287-4a02-8abd-b1f1835678b5/WhatsApp_Image_2022-04-05_at_3.10.58_PM.jpeg?X-Amz-Algorithm=AWS4-HMAC-SHA256&X-Amz-Content-Sha256=UNSIGNED-PAYLOAD&X-Amz-Credential=AKIAT73L2G45EIPT3X45%2F20230504%2Fus-west-2%2Fs3%2Faws4_request&X-Amz-Date=20230504T091047Z&X-Amz-Expires=3600&X-Amz-Signature=5b6564552d889a522e4bd4fdbb86245025fc55bbb49751a1d5fb82eabf52d118&X-Amz-SignedHeaders=host&x-id=GetObject",
      "https://s3.us-west-2.amazonaws.com/secure.notion-static.com/64b4f5da-d041-44ab-adee-5e22fd8732d9/WhatsApp_Image_2022-04-05_at_3.36.02_PM.jpeg?X-Amz-Algorithm=AWS4-HMAC-SHA256&X-Amz-Content-Sha256=UNSIGNED-PAYLOAD&X-Amz-Credential=AKIAT73L2G45EIPT3X45%2F20230504%2Fus-west-2%2Fs3%2Faws4_request&X-Amz-Date=20230504T091047Z&X-Amz-Expires=3600&X-Amz-Signature=f851c190d82eda2505a29694e3e7ede9e22daa29798f6c98aee335ca3f7ccf7c&X-Amz-SignedHeaders=host&x-id=GetObject",
      "https://s3.us-west-2.amazonaws.com/secure.notion-static.com/da7dd1e9-c9f3-4aaa-8568-5b402073d1fa/WhatsApp_Image_2022-04-05_at_3.35.21_PM.jpeg?X-Amz-Algorithm=AWS4-HMAC-SHA256&X-Amz-Content-Sha256=UNSIGNED-PAYLOAD&X-Amz-Credential=AKIAT73L2G45EIPT3X45%2F20230504%2Fus-west-2%2Fs3%2Faws4_request&X-Amz-Date=20230504T091047Z&X-Amz-Expires=3600&X-Amz-Signature=16465d58e86ae9fff55fe3e4cebbbd0f0f2760e5e8420948fa99e28961e4fd62&X-Amz-SignedHeaders=host&x-id=GetObject",
      "https://s3.us-west-2.amazonaws.com/secure.notion-static.com/b996154c-3cbf-4dea-8963-1a0d549ad04c/WhatsApp_Image_2022-04-05_at_3.33.56_PM.jpeg?X-Amz-Algorithm=AWS4-HMAC-SHA256&X-Amz-Content-Sha256=UNSIGNED-PAYLOAD&X-Amz-Credential=AKIAT73L2G45EIPT3X45%2F20230504%2Fus-west-2%2Fs3%2Faws4_request&X-Amz-Date=20230504T091047Z&X-Amz-Expires=3600&X-Amz-Signature=89fe5e6d1c5a6197a45a849c09208f6c092448cdd5ec4f4644ae1faa7c5108f6&X-Amz-SignedHeaders=host&x-id=GetObject",
      "https://s3.us-west-2.amazonaws.com/secure.notion-static.com/636173ad-3e04-4784-acef-aa5f690149e1/WhatsApp_Image_2022-04-05_at_3.34.30_PM.jpeg?X-Amz-Algorithm=AWS4-HMAC-SHA256&X-Amz-Content-Sha256=UNSIGNED-PAYLOAD&X-Amz-Credential=AKIAT73L2G45EIPT3X45%2F20230504%2Fus-west-2%2Fs3%2Faws4_request&X-Amz-Date=20230504T091047Z&X-Amz-Expires=3600&X-Amz-Signature=6c8a4b281dae1cb573db6329751da3048109329f6d93f007cac6d50d3d249413&X-Amz-SignedHeaders=host&x-id=GetObject"
    ],
    "Campus Manager": "Supriya Gaikwad",
    "Map": "https://www.google.com/maps/embed?pb=!1m18!1m12!1m3!1d3785.0299202633305!2d73.8705823148915!3d18.436950587457755!2m3!1f0!2f0!3f0!3m2!1i1024!2i768!4f13.1!3m3!1m2!1s0x3bc2ebaca984f343%3A0xc9f4b1cf5b8143ee!2sNavGurukul%20Pune%20Campus!5e0!3m2!1sen!2sin!4v1648272116508!5m2!1sen!2sin",
    "Avatar": "https://s3.us-west-2.amazonaws.com/secure.notion-static.com/322cf5dc-5254-43ff-934f-8f335836f1ea/avatar.png?X-Amz-Algorithm=AWS4-HMAC-SHA256&X-Amz-Content-Sha256=UNSIGNED-PAYLOAD&X-Amz-Credential=AKIAT73L2G45EIPT3X45%2F20230504%2Fus-west-2%2Fs3%2Faws4_request&X-Amz-Date=20230504T091047Z&X-Amz-Expires=3600&X-Amz-Signature=b07fdc9be1773a53dd7c18907461f970fd47ffe5d99a2788ca06330d969899a0&X-Amz-SignedHeaders=host&x-id=GetObject",
    "Contact": "supriya@navgurukul.org",
    "Address": "F2, Narmada City, Gujar-Nimbalkarwadi, Gujarwadi Rd, near waghjai mata Mandir, Katraj, Pune, Maharashtra 411046",
    "Student Capacity": "200",
    "Name": "Pune Campus",
    "Content": []
  }
}