{
  "caf4161d-4295-4137-a677-9ae2236893d9": {
    "Website": "https://www.amazon.in/",
    "Logo": "https://s3.us-west-2.amazonaws.com/secure.notion-static.com/5566be96-8706-4f63-90a1-520acdacea95/amazon.png?X-Amz-Algorithm=AWS4-HMAC-SHA256&X-Amz-Content-Sha256=UNSIGNED-PAYLOAD&X-Amz-Credential=AKIAT73L2G45EIPT3X45%2F20230512%2Fus-west-2%2Fs3%2Faws4_request&X-Amz-Date=20230512T114130Z&X-Amz-Expires=3600&X-Amz-Signature=a594ac80f257c845c9ac8132635b8e04c670f8a851d2a85ed0507b7df43a52f9&X-Amz-SignedHeaders=host&x-id=GetObject",
    "Supporter Name": "Amazon",
    "Content": []
  },
  "3967f0ab-22bc-49cb-952e-2cbcf997a59e": {
    "Website": "http://ncore.thenudge.org/",
    "Logo": "https://s3.us-west-2.amazonaws.com/secure.notion-static.com/5d68e179-0b09-436c-aec1-b60c778fa20a/ncore.jpg?X-Amz-Algorithm=AWS4-HMAC-SHA256&X-Amz-Content-Sha256=UNSIGNED-PAYLOAD&X-Amz-Credential=AKIAT73L2G45EIPT3X45%2F20230512%2Fus-west-2%2Fs3%2Faws4_request&X-Amz-Date=20230512T114130Z&X-Amz-Expires=3600&X-Amz-Signature=9a08a5ee0d2c7e5e1e2d7c55fface2277c402b8b176c6371cf8d9bd7cb015bb9&X-Amz-SignedHeaders=host&x-id=GetObject",
    "Supporter Name": "N Core",
    "Content": []
  },
  "9dbe03cc-f85c-4cf7-aea1-493c6d089beb": {
    "Website": "https://www.socialalpha.org/",
    "Logo": "https://s3.us-west-2.amazonaws.com/secure.notion-static.com/755dd5bc-e08a-4b97-840f-d8dc5648ca00/social-alpha.jpg?X-Amz-Algorithm=AWS4-HMAC-SHA256&X-Amz-Content-Sha256=UNSIGNED-PAYLOAD&X-Amz-Credential=AKIAT73L2G45EIPT3X45%2F20230512%2Fus-west-2%2Fs3%2Faws4_request&X-Amz-Date=20230512T114130Z&X-Amz-Expires=3600&X-Amz-Signature=49d1583bf58a6d81da35f1eadb8be3c1c706d002f394b966229b7d6038587bae&X-Amz-SignedHeaders=host&x-id=GetObject",
    "Supporter Name": "Social Alpha",
    "Content": []
  },
  "c491dd45-d096-4e1e-ac11-4c74eb50a1fe": {
    "Website": "https://unltdindia.org/",
    "Logo": "https://s3.us-west-2.amazonaws.com/secure.notion-static.com/9be384ec-d6aa-4e83-90d1-df95cd97e7b5/unltd.jpg?X-Amz-Algorithm=AWS4-HMAC-SHA256&X-Amz-Content-Sha256=UNSIGNED-PAYLOAD&X-Amz-Credential=AKIAT73L2G45EIPT3X45%2F20230512%2Fus-west-2%2Fs3%2Faws4_request&X-Amz-Date=20230512T114130Z&X-Amz-Expires=3600&X-Amz-Signature=948d22cfe7fb699d92e81305510fc77f3f611ad260b74a3e164e375b74fcd73d&X-Amz-SignedHeaders=host&x-id=GetObject",
    "Supporter Name": "Un Ltd",
    "Content": []
  },
  "ddf0639d-ad4a-4893-a74c-b1c218b3dab8": {
    "Website": "https://www.dunnhumby.com/india/",
    "Logo": "https://s3.us-west-2.amazonaws.com/secure.notion-static.com/36642d4a-94a9-433f-a37f-58d06973c672/dunnhumby_logo.png?X-Amz-Algorithm=AWS4-HMAC-SHA256&X-Amz-Content-Sha256=UNSIGNED-PAYLOAD&X-Amz-Credential=AKIAT73L2G45EIPT3X45%2F20230512%2Fus-west-2%2Fs3%2Faws4_request&X-Amz-Date=20230512T114130Z&X-Amz-Expires=3600&X-Amz-Signature=33b3bfbb13c6823a6616e9bb9ea0d5b29efee77c11fd939e6e64e6b089d743ab&X-Amz-SignedHeaders=host&x-id=GetObject",
    "Supporter Name": "Dunnhumby",
    "Content": []
  },
  "16a94c34-c589-4155-998c-dc36d953ce46": {
    "Website": "https://www.games24x7.com/",
    "Logo": "https://s3.us-west-2.amazonaws.com/secure.notion-static.com/55072092-0b71-4c6d-b199-d0e2a1c43f89/games24x7.png?X-Amz-Algorithm=AWS4-HMAC-SHA256&X-Amz-Content-Sha256=UNSIGNED-PAYLOAD&X-Amz-Credential=AKIAT73L2G45EIPT3X45%2F20230512%2Fus-west-2%2Fs3%2Faws4_request&X-Amz-Date=20230512T114130Z&X-Amz-Expires=3600&X-Amz-Signature=a1186f2ac9acabbbb3dc129529525e70ff03ca1174bad789b4bd99d085923d4a&X-Amz-SignedHeaders=host&x-id=GetObject",
    "Supporter Name": "Games 24x7",
    "Content": []
  },
  "5847d604-dd8d-4916-a9be-6e3560274f2f": {
    "Website": "https://www.accenture.com/in-en",
    "Logo": "https://s3.us-west-2.amazonaws.com/secure.notion-static.com/f01e8dfd-939b-49e8-8a44-631c5f25b1b6/accenture.jpg?X-Amz-Algorithm=AWS4-HMAC-SHA256&X-Amz-Content-Sha256=UNSIGNED-PAYLOAD&X-Amz-Credential=AKIAT73L2G45EIPT3X45%2F20230512%2Fus-west-2%2Fs3%2Faws4_request&X-Amz-Date=20230512T114130Z&X-Amz-Expires=3600&X-Amz-Signature=3b845fa545448ed1f05029bf71a40fd881930ab59ccb9e2b7951d3a08065ca6c&X-Amz-SignedHeaders=host&x-id=GetObject",
    "Supporter Name": "Accenture",
    "Content": []
  },
  "783469ef-a4c5-441c-adc6-a6db4b92ab6a": {
    "Website": "https://www.microsoft.com/en-in",
    "Logo": "https://s3.us-west-2.amazonaws.com/secure.notion-static.com/c47bcc48-6390-4689-87c5-7122ceec3a2b/microsoft.jpg?X-Amz-Algorithm=AWS4-HMAC-SHA256&X-Amz-Content-Sha256=UNSIGNED-PAYLOAD&X-Amz-Credential=AKIAT73L2G45EIPT3X45%2F20230512%2Fus-west-2%2Fs3%2Faws4_request&X-Amz-Date=20230512T114130Z&X-Amz-Expires=3600&X-Amz-Signature=78d6f4c5f52b6745e96aa3790c9f989e5fee3986dc470f9fd6a0f2ba84d1c4d6&X-Amz-SignedHeaders=host&x-id=GetObject",
    "Supporter Name": "Microsoft",
    "Content": []
  }
}